awslabs/__init__.py
awslabs/amazon_qindex_mcp_server/__init__.py
awslabs/amazon_qindex_mcp_server/clients.py
awslabs/amazon_qindex_mcp_server/server.py
awslabs_amazon_qindex_mcp_server-0.0.9.dist-info/METADATA
awslabs_amazon_qindex_mcp_server-0.0.9.dist-info/WHEEL
awslabs_amazon_qindex_mcp_server-0.0.9.dist-info/entry_points.txt
awslabs_amazon_qindex_mcp_server-0.0.9.dist-info/licenses/LICENSE
awslabs_amazon_qindex_mcp_server-0.0.9.dist-info/licenses/NOTICE
awslabs_amazon_qindex_mcp_server-0.0.9.dist-info/RECORD
