Metadata-Version: 2.4
Name: awslabs.amazon-qindex-mcp-server
Version: 0.0.9
Summary: This is an AWS Labs Model Context Protocol (MCP) server implementation that enables Independent Software Vendors (ISVs) to interact with Amazon Q Business's search capabilities. The server facilitates searching across enterprise customers' Q index using the SearchRelevantContent API.
Project-URL: homepage, https://awslabs.github.io/mcp/
Project-URL: docs, https://awslabs.github.io/mcp/servers/amazon-qindex-mcp-server/
Project-URL: documentation, https://awslabs.github.io/mcp/servers/amazon-qindex-mcp-server/
Project-URL: repository, https://github.com/awslabs/mcp.git
Project-URL: changelog, https://github.com/awslabs/mcp/blob/main/src/amazon-qindex-mcp-server/CHANGELOG.md
Author: Amazon Web Services
Author-email: AWSLabs MCP <203918161+awslabs-mcp@users.noreply.github.com>, Akhilesh Amara <suryaakhileshamara@gmail.com>, Takeshi Kobayashi <tkoba-aws@users.noreply.github.com>
License: Apache-2.0
License-File: LICENSE
License-File: NOTICE
Classifier: License :: OSI Approved :: Apache Software License
Classifier: Operating System :: OS Independent
Classifier: Programming Language :: Python
Classifier: Programming Language :: Python :: 3
Classifier: Programming Language :: Python :: 3.10
Classifier: Programming Language :: Python :: 3.11
Classifier: Programming Language :: Python :: 3.12
Classifier: Programming Language :: Python :: 3.13
Requires-Python: >=3.10
Requires-Dist: boto3>=1.37.24
Requires-Dist: loguru>=0.7.0
Requires-Dist: mcp[cli]>=1.23.0
Requires-Dist: pydantic>=2.10.6
